LICENSE
README.md
setup.py
matrixlab/__init__.py
matrixlab/utils.py
matrixlab.egg-info/PKG-INFO
matrixlab.egg-info/SOURCES.txt
matrixlab.egg-info/dependency_links.txt
matrixlab.egg-info/requires.txt
matrixlab.egg-info/top_level.txt