Metadata-Version: 2.2
Name: matrixlab
Version: 0.0.1
Summary: A numerical linear algebra library in native Python
Home-page: https://github.com/PEQUAN/matrixlab.git
Author: matrixlab team
Author-email: xinyechenai@gmail.com
Maintainer: matrixlab team
Maintainer-email: xinyechenai@gmail.com
License: MIT License
Classifier: Intended Audience :: Science/Research
Classifier: Intended Audience :: Developers
Classifier: Programming Language :: Python
Classifier: Topic :: Software Development
Classifier: Topic :: Scientific/Engineering
Classifier: Operating System :: Microsoft :: Windows
Classifier: Operating System :: Unix
Classifier: Programming Language :: Python :: 3
License-File: LICENSE
Requires-Dist: numpy>=1.7.2
Dynamic: author
Dynamic: author-email
Dynamic: classifier
Dynamic: description
Dynamic: description-content-type
Dynamic: home-page
Dynamic: license
Dynamic: maintainer
Dynamic: maintainer-email
Dynamic: requires-dist
Dynamic: summary
